mriaug/__init__.py
mriaug/core.py
mriaug/utils.py
mriaug-0.1.1.dist-info/LICENSE
mriaug-0.1.1.dist-info/METADATA
mriaug-0.1.1.dist-info/WHEEL
mriaug-0.1.1.dist-info/RECORD
